README.md
setup.py
fluidattacks/__init__.py
fluidattacks.egg-info/PKG-INFO
fluidattacks.egg-info/SOURCES.txt
fluidattacks.egg-info/dependency_links.txt
fluidattacks.egg-info/top_level.txt